korvax-0.2.0.dist-info/RECORD
korvax-0.2.0.dist-info/WHEEL
korvax-0.2.0.dist-info/METADATA
korvax-0.2.0.dist-info/licenses/LICENSE-3RD-PARTY
korvax-0.2.0.dist-info/licenses/LICENSE
korvax/_resample.py
korvax/_typing.py
korvax/util.py
korvax/convert.py
korvax/__init__.py
korvax/loss.py
korvax/py.typed
korvax/pitch/__init__.py
korvax/pitch/_yin.py
korvax/pitch/viterbi.py
korvax/.dylibs/libomp.dylib
korvax/transforms/__init__.py
korvax/transforms/mel.py
korvax/transforms/fourier.py
korvax/filter/__init__.py
korvax/filter/_allpole.py
korvax/filter/_filter_cpu.cpython-314-darwin.so
korvax/filter/csrc/filter_gpu.cu
korvax/filter/csrc/filter_cpu.cc
korvax/filter/csrc/_common.h
