Metadata-Version: 2.4
Name: korvax
Version: 0.2.0
Summary: JAX utilities for Audio DSP and ML
Author-Email: David Marttila <david.suedholt@gmail.com>
License-Expression: MIT
License-File: LICENSE
License-File: LICENSE-3RD-PARTY
Classifier: Development Status :: 3 - Alpha
Classifier: Intended Audience :: Developers
Classifier: Programming Language :: Python :: 3
Classifier: Programming Language :: Python :: 3.11
Classifier: Programming Language :: Python :: 3.12
Classifier: Programming Language :: Python :: 3.13
Classifier: Programming Language :: Python :: 3.14
Project-URL: Homepage, https://korvax.readthedocs.io/
Project-URL: Documentation, https://korvax.readthedocs.io/
Project-URL: Repository, https://github.com/davidmarttila/korvax
Requires-Python: >=3.11
Requires-Dist: jax>=0.6.2
Requires-Dist: jaxtyping>=0.3.3
Provides-Extra: cuda12
Requires-Dist: jax[cuda12]; sys_platform == "linux" and extra == "cuda12"
Provides-Extra: cuda13
Requires-Dist: jax[cuda13]; sys_platform == "linux" and extra == "cuda13"
